LICENSE
github/__init__.py
github/github_client.py
github/methods/__init__.py
github/methods/activity/__init__.py
github/methods/activity/events/__init__.py
github/methods/activity/events/list_a_user_events.py
github/methods/activity/events/list_a_user_public_events.py
github/methods/activity/events/list_network_repository_events.py
github/methods/activity/events/list_public_events.py
github/methods/activity/events/list_public_organization_events.py
github/methods/activity/events/list_repository_events.py
github/methods/activity/events/list_user_events.py
github/methods/activity/events/list_user_organization_events.py
github/methods/activity/events/list_user_received_events.py
github/methods/activity/feeds/__init__.py
github/methods/activity/notifications/__init__.py
github/methods/activity/starring/__init__.py
github/methods/activity/starring/is_repository_starred_by_me.py
github/methods/activity/starring/list_repository_stargazers.py
github/methods/activity/starring/list_starred_repositories.py
github/methods/activity/starring/list_user_starred_repositories.py
github/methods/activity/starring/star_repository.py
github/methods/activity/starring/unstar_repository.py
github/methods/activity/watching/__init__.py
github/methods/activity/watching/delete_repository_subscription.py
github/methods/activity/watching/get_repository_subscription.py
github/methods/activity/watching/list_repository_watchers.py
github/methods/activity/watching/list_user_watched_repositories.py
github/methods/activity/watching/list_watched_repositories.py
github/methods/activity/watching/set_repository_subscription.py
github/methods/auth/__init__.py
github/methods/auth/authenticate_user.py
github/methods/base/__init__.py
github/methods/base/delete_with_token.py
github/methods/base/get_with_token.py
github/methods/base/patch_with_token.py
github/methods/base/post_with_token.py
github/methods/base/put_with_token.py
github/methods/organizations/__init__.py
pyghc-0.1.0.dist-info/LICENSE
pyghc-0.1.0.dist-info/WHEEL
pyghc-0.1.0.dist-info/METADATA
pyghc-0.1.0.dist-info/RECORD
